[
  {
    "id": 1759601563047,
    "customerInfo": {
      "fullName": "Mohammadasif Jirayat",
      "email": "asifjirayat@gmail.com",
      "phone": "07411451817",
      "address": "Belgaum"
    },
    "cartItems": [
      {
        "id": 2,
        "name": "Crispy Fries",
        "description": "Golden crispy potato fries with sea salt",
        "price": 5.99,
        "category": "sides",
        "image": "/images/fries.jpg",
        "available": true,
        "quantity": 1
      }
    ],
    "totalAmount": 5.99,
    "payment": {
      "cardNumber": "234",
      "expiry": "23",
      "cvc": "23"
    },
    "status": "pending",
    "orderDate": "2025-10-04T18:12:43.047Z",
    "estimatedDelivery": "2025-10-04T18:42:43.047Z"
  },
  {
    "id": 1759722094501,
    "customerInfo": {
      "fullName": "Mohammadasif Jirayat",
      "email": "asifjirayat@gmail.com",
      "phone": "07411451817",
      "address": "Belgaum"
    },
    "cartItems": [
      {
        "id": 3,
        "name": "Margherita Pizza",
        "description": "Fresh mozzarella, tomato sauce, and basil on our signature thin crust",
        "price": 16.99,
        "category": "pizza",
        "image": "/images/pizza.jpg",
        "available": true,
        "preparationTime": "15-20 mins",
        "quantity": 1
      }
    ],
    "totalAmount": 16.99,
    "payment": {
      "cardNumber": "121",
      "expiry": "12",
      "cvc": "12"
    },
    "status": "pending",
    "orderDate": "2025-10-06T03:41:34.501Z",
    "estimatedDelivery": "2025-10-06T04:11:34.501Z"
  }
]
